<?xml version="1.0" encoding="UTF-8"?>
<databaseChangeLog xmlns="http://www.liquibase.org/xml/ns/dbchangelog"
                   xmlns:xsi="http://www.w3.org/2001/XMLSchema-instance"
                   xsi:schemaLocation="http://www.liquibase.org/xml/ns/dbchangelog
                   http://www.liquibase.org/xml/ns/dbchangelog/dbchangelog-latest.xsd">

    <changeSet id="create-table-configuracao-sistema" author="elielson.silva">
        <createTable tableName="configuracao_sistema">
            <column name="id" type="uuid" defaultValueComputed="gen_random_uuid()">
                <constraints primaryKey="true" nullable="false"/>
            </column>
            <column name="key" type="varchar(100)">
                <constraints nullable="false" unique="true"/>
            </column>
            <column name="valor" type="varchar(500)">
                <constraints nullable="true"/>
            </column>
            <column name="descricao" type="varchar(200)">
                <constraints nullable="true"/>
            </column>
        </createTable>
    </changeSet>

</databaseChangeLog>
